psclient/__init__.py
psclient/chatlog.py
ps_client-0.0.8.dist-info/LICENSE
ps_client-0.0.8.dist-info/METADATA
ps_client-0.0.8.dist-info/WHEEL
ps_client-0.0.8.dist-info/pbr.json
ps_client-0.0.8.dist-info/top_level.txt
ps_client-0.0.8.dist-info/RECORD
