Metadata-Version: 2.1
Name: ps-client
Version: 0.0.8
Summary: A package for interactions with the Pokémon Showdown simulator.
Home-page: https://github.com/AnnikaCodes/ps-client
Author: Annika
Author-email: annika0uwu@gmail.com
License: UNKNOWN
Platform: UNKNOWN
Classifier: Programming Language :: Python :: 3
Classifier: License :: OSI Approved :: MIT License
Classifier: Operating System :: OS Independent
Requires-Python: >=3.6
Requires-Dist: pytz
Requires-Dist: requests
Requires-Dist: websocket-client
